[
  {
    "provider": "cloud",
    "task": "Current Stock Price",
    "linear_energy_j": {
      "mean": 6.813430333333334,
      "std": 5.5322257739656955,
      "ci_lower": -6.929380341692007,
      "ci_upper": 20.556241008358676,
      "min": 3.02203,
      "max": 13.1616,
      "n": 3
    },
    "agentic_energy_j": {
      "mean": 26.152834333333335,
      "std": 14.540834593377449,
      "ci_lower": -9.968601240399362,
      "ci_upper": 62.27426990706603,
      "min": 12.003454,
      "max": 41.055816,
      "n": 3
    },
    "orchestration_tax": {
      "mean": 5.182285779921633,
      "std": 3.997499003942012,
      "ci_lower": -4.7480522484550995,
      "ci_upper": 15.112623808298366,
      "min": 1.9297982768052515,
      "max": 9.64507533017076,
      "n": 3
    }
  }
]